aenir/.create_table_from_csv.py
aenir/__init__.py
aenir/_exceptions.py
aenir/_logging.py
aenir/games.py
aenir/morph.py
aenir/skeleton.py
aenir/stats.py
aenir/static/stat-tables.ods
aenir/static/binding-blade/cleaned_stats.db
aenir/static/blazing-sword/cleaned_stats.db
aenir/static/genealogy-of-the-holy-war/cleaned_stats.db
aenir/static/path-of-radiance/cleaned_stats.db
aenir/static/the-sacred-stones/cleaned_stats.db
aenir/static/thracia-776/cleaned_stats.db
aenir-0.42.post1.dev652.dist-info/licenses/LICENSE.txt
aenir-0.42.post1.dev652.dist-info/METADATA
aenir-0.42.post1.dev652.dist-info/WHEEL
aenir-0.42.post1.dev652.dist-info/top_level.txt
aenir-0.42.post1.dev652.dist-info/RECORD
