Metadata-Version: 2.4
Name: aenir
Version: 0.42.post1.dev652
Summary: Stat calculator for Fire Emblem
Home-page: https://github.com/gchang12/aenir/
Author: gchang12
Author-email: gc8@hawaii.edu
License: MIT
Project-URL: Source, https://github.com/gchang12/aenir/
Project-URL: Download, https://pypi.org/project/aenir/
Platform: any
Classifier: Development Status :: 4 - Beta
Classifier: Programming Language :: Python
License-File: LICENSE.txt
Requires-Dist: importlib-metadata; python_version < "3.8"
Provides-Extra: testing
Requires-Dist: setuptools; extra == "testing"
Requires-Dist: pytest; extra == "testing"
Requires-Dist: pytest-cov; extra == "testing"
Dynamic: license-file
